passx/__init__.py
passx/passx.py
passx-0.0.7.dist-info/LICENSE
passx-0.0.7.dist-info/METADATA
passx-0.0.7.dist-info/WHEEL
passx-0.0.7.dist-info/entry_points.txt
passx-0.0.7.dist-info/top_level.txt
passx-0.0.7.dist-info/RECORD
