Metadata-Version: 2.1
Name: passx
Version: 0.0.7
Summary: A Password manager using GNUPG
Home-page: https://github.com/harshbaliyan126/Passx-py
Author: floppy04 <Harsh Baliyan>
Author-email: <harshbaliyan126@gmail.com>
License: UNKNOWN
Platform: UNKNOWN
Classifier: Development Status :: 1 - Planning
Classifier: Intended Audience :: Developers
Classifier: Programming Language :: Python :: 3
Classifier: Operating System :: Unix
Classifier: Operating System :: MacOS :: MacOS X
Classifier: Operating System :: Microsoft :: Windows
License-File: LICENSE
Requires-Dist: appdirs (==1.4.4)
Requires-Dist: fs (==2.4.13)
Requires-Dist: pyperclip (==1.8.2)
Requires-Dist: python-gnupg (==0.4.7)
Requires-Dist: pytz (==2021.1)
Requires-Dist: six (==1.15.0)
